fingrid/__init__.py
fingrid/client.py
fingrid/config.yml
fingrid/endpoint.py
fingrid/utils.py
fingrid_py-0.1.0.dist-info/WHEEL
fingrid_py-0.1.0.dist-info/METADATA
fingrid_py-0.1.0.dist-info/RECORD
