Metadata-Version: 2.3
Name: fingrid-py
Version: 0.1.0
Summary: Python client for Fingrid API
Keywords: fingrid,fingrid-py,py-fingrid,fingrid-api,fingrid API,fingrid avoindata
Requires-Dist: pandas>=2.3.2
Requires-Dist: pyyaml>=6.0.2
Requires-Dist: requests>=2.32.3
Requires-Python: >=3.12
